{"OutputFileHashSum":"E262B1C97A38AF0B6EA287BBFCF90FC1DAEB3E4315EE113E79668B988C90CA60","Converted":true,"OutputModifyDate":"2022-04-03T04:36:18.6718329Z","Metadatas":[],"MetadataTypes":[{"CategoryName":"VuGen.Replay","MetadataTypeName":"HP.LR.Vugen.Iteration","Id":1},{"CategoryName":"VuGen.Replay","MetadataTypeName":"HP.LR.Vugen.NotifyParameterSubstitution","Id":2},{"CategoryName":"VuGen.Replay","MetadataTypeName":"HP.LR.Vugen.NotifySavingParameter","Id":3},{"CategoryName":"VuGen.Replay","MetadataTypeName":"HP.LR.Vugen.NotifyAny","Id":4},{"CategoryName":"VuGen.Replay","MetadataTypeName":"Utt.Debugger.Warning","Id":5},{"CategoryName":"VuGen.Replay","MetadataTypeName":"Utt.Debugger.Error","Id":6}]}